README.rst
setup.py
hawkular/__init__.py
hawkular/alerts.py
hawkular/client.py
hawkular/metrics.py
hawkular_client.egg-info/PKG-INFO
hawkular_client.egg-info/SOURCES.txt
hawkular_client.egg-info/dependency_links.txt
hawkular_client.egg-info/top_level.txt