Metadata-Version: 1.1
Name: hawkular-client
Version: 0.5.5
Summary: Python client to communicate with Hawkular server over HTTP(S)
Home-page: http://github.com/hawkular/hawkular-client-python
Author: Michael Burman
Author-email: miburman@redhat.com
License: Apache License 2.0
Platform: UNKNOWN
Classifier: Development Status :: 5 - Production/Stable
Classifier: Intended Audience :: Developers
Classifier: Programming Language :: Python
Classifier: Programming Language :: Python :: 2
Classifier: Programming Language :: Python :: 3
Classifier: Topic :: System :: Monitoring
